lancetnic/__init__.py
lancetnic/setup.py
lancetnic/engine/__init__.py
lancetnic/engine/base_trainer.py
lancetnic/engine/trainer.py
lancetnic/models/__init__.py
lancetnic/models/class_model.py
lancetnic/utils/__init__.py
lancetnic/utils/dir_runs.py
lancetnic/utils/metrics.py
lancetnic-2.1.0.dist-info/LICENSE
lancetnic-2.1.0.dist-info/METADATA
lancetnic-2.1.0.dist-info/WHEEL
lancetnic-2.1.0.dist-info/top_level.txt
lancetnic-2.1.0.dist-info/RECORD
