Metadata-Version: 2.1
Name: lancetnic
Version: 2.1.0
Summary: A tool for working with text data
Home-page: https://github.com/Lancet52/lancetnic
Author: Lancet52
Author-email: lancetFPV@yandex.ru
Classifier: Development Status :: 5 - Production/Stable
Classifier: Programming Language :: Python :: 3.10
Classifier: License :: OSI Approved :: MIT License
Classifier: Operating System :: OS Independent
Requires-Python: >=3.9
License-File: LICENSE
Requires-Dist: torch==2.5.1
Requires-Dist: torchaudio==2.5.1
Requires-Dist: torchvision==0.20.1
Requires-Dist: scikit-learn==1.6.1
Requires-Dist: pandas==2.2.3
Requires-Dist: matplotlib==3.10.1
Requires-Dist: seaborn==0.13.2
Requires-Dist: tqdm==4.67.1
Requires-Dist: PyYaml==6.0.3
